AUTHORS.rst
CONTRIBUTING.rst
HISTORY.rst
LICENSE
MANIFEST.in
README.rst
setup.cfg
setup.py
flask_musers/__init__.py
flask_musers/forms.py
flask_musers/models.py
flask_musers/utils.py
flask_musers/validators.py
flask_musers/views.py
flask_musers.egg-info/PKG-INFO
flask_musers.egg-info/SOURCES.txt
flask_musers.egg-info/dependency_links.txt
flask_musers.egg-info/not-zip-safe
flask_musers.egg-info/requires.txt
flask_musers.egg-info/top_level.txt