Metadata-Version: 1.1
Name: flask-musers
Version: 0.5.4
Summary: Flask app for store user in MongoDB and simple views for login, logout and registration.
Home-page: https://github.com/s-m-i-t-a/flask-musers
Author: Jindřich Smitka
Author-email: smitka.j@gmail.com
License: BSD
Keywords: flask-musers
Platform: UNKNOWN
Classifier: Development Status :: 2 - Pre-Alpha
Classifier: Intended Audience :: Developers
Classifier: License :: OSI Approved :: BSD License
Classifier: Natural Language :: English
Classifier: Programming Language :: Python :: 2
Classifier: Programming Language :: Python :: 2.6
Classifier: Programming Language :: Python :: 2.7
Classifier: Programming Language :: Python :: 3
Classifier: Programming Language :: Python :: 3.3
Classifier: Programming Language :: Python :: 3.4
